{"id":"f4e65d7d-f949-4ee9-b0f6-17e5d73d0b55","entity_type":"relationship","agent":"default","timestamp":"2026-01-17T21:51:18.244696809Z","data":{"entity":{"entity":{"active":true,"agent":"default","constraints":{"allow_cycles":true,"max_inbound":null,"max_outbound":null,"source_types":null,"target_types":null},"description":null,"direction":"Unidirectional","id":"f4e65d7d-f949-4ee9-b0f6-17e5d73d0b55","metadata":{},"relationship_type":"References","source_id":"4d5c7602-e80e-44aa-9355-f759577bffd9","source_type":"task","strength":"Medium","target_id":"76479877-c18d-4ce8-b22a-258d614b6a23","target_type":"reasoning","timestamp":"2026-01-17T21:51:18.244696809Z"}}},"content_hash":"959ab049382e151394febf45b2a2d51e95c861860ddbc99efd51026dcf5e70ca","size_bytes":523,"tags":[],"references":[],"metadata":{}}