{"id":"96e9bc31-2f21-4e32-81c5-ff12301e6706","entity_type":"task","agent":"default","timestamp":"2026-01-17T21:57:40.982664056Z","data":{"entity":{"agent":"default","description":"","end_time":null,"id":"96e9bc31-2f21-4e32-81c5-ff12301e6706","priority":"medium","start_time":"2026-01-17T21:57:40.982664056Z","status":"todo","title":"Add commit SHA and build info to engram --version output"}},"content_hash":"bb6f7428a1bb93867d941625608992904cef5d51eb2f2ce4100e361413687394","size_bytes":256,"tags":[],"references":[],"metadata":{}}