{"id":"f33787ff-5ea7-4544-84f3-d455203fbb6e","entity_type":"context","agent":"default","timestamp":"2026-01-18T04:13:39.691321230Z","data":{"entity":{"agent":"default","content":"","created_at":"2026-01-18T04:13:39.691321230Z","id":"f33787ff-5ea7-4544-84f3-d455203fbb6e","relevance":"medium","source":"","source_id":null,"title":"NLQ relationship testing context","updated_at":"2026-01-18T04:13:39.691321230Z"}},"content_hash":"5ba7a5e348a0a8180e56680ffc63349cf51f9c1c100a9846a3dc0a27c2d56929","size_bytes":272,"tags":[],"references":[],"metadata":{}}